{
"res":{
	"d0000": {"x":0,"y":0,"w":220,"h":190},
	"d0001": {"x":220,"y":0,"w":220,"h":190},
	"d0002": {"x":440,"y":0,"w":220,"h":190},
	"d0003": {"x":660,"y":0,"w":220,"h":190},
	"d0004": {"x":0,"y":190,"w":220,"h":190},
	"d0005": {"x":220,"y":190,"w":220,"h":190},
	"d0006": {"x":440,"y":190,"w":220,"h":190},
	"d0007": {"x":660,"y":190,"w":220,"h":190},
	"d0008": {"x":0,"y":380,"w":220,"h":190},
	"d0009": {"x":0,"y":0,"w":220,"h":190},
	"e0000": {"x":220,"y":380,"w":220,"h":190},
	"e0001": {"x":440,"y":380,"w":220,"h":190},
	"e0002": {"x":660,"y":380,"w":220,"h":190},
	"e0003": {"x":0,"y":570,"w":220,"h":190},
	"e0004": {"x":660,"y":380,"w":220,"h":190},
	"e0005": {"x":220,"y":570,"w":220,"h":190},
	"e0006": {"x":220,"y":380,"w":220,"h":190},
	"f0000": {"x":440,"y":570,"w":220,"h":190},
	"f0001": {"x":660,"y":570,"w":220,"h":190},
	"f0002": {"x":0,"y":760,"w":220,"h":190},
	"f0003": {"x":220,"y":760,"w":220,"h":190},
	"f0004": {"x":440,"y":760,"w":220,"h":190},
	"f0005": {"x":660,"y":760,"w":220,"h":190},
	"f0006": {"x":0,"y":950,"w":220,"h":190},
	"f0007": {"x":220,"y":950,"w":220,"h":190},
	"f0008": {"x":440,"y":950,"w":220,"h":190},
	"f0009": {"x":440,"y":570,"w":220,"h":190}
},
"frames": {
	"d": {
		"totalFrame": 10,
		"childrenFrame": [
			{"res":"d0000","x":0,"y":0},
			{"res":"d0001","x":0,"y":0},
			{"res":"d0002","x":0,"y":0},
			{"res":"d0003","x":0,"y":0},
			{"res":"d0004","x":0,"y":0},
			{"res":"d0005","x":0,"y":0},
			{"res":"d0006","x":0,"y":0},
			{"res":"d0007","x":0,"y":0},
			{"res":"d0008","x":0,"y":0},
			{"res":"d0009","x":0,"y":0}
		]
	},
	"e": {
		"totalFrame": 7,
		"childrenFrame": [
			{"res":"e0000","x":0,"y":0},
			{"res":"e0001","x":0,"y":0},
			{"res":"e0002","x":0,"y":0},
			{"res":"e0003","x":0,"y":0},
			{"res":"e0004","x":0,"y":0},
			{"res":"e0005","x":0,"y":0},
			{"res":"e0006","x":0,"y":0}
		]
	},
	"f": {
		"totalFrame": 10,
		"childrenFrame": [
			{"res":"f0000","x":0,"y":0},
			{"res":"f0001","x":0,"y":0},
			{"res":"f0002","x":0,"y":0},
			{"res":"f0003","x":0,"y":0},
			{"res":"f0004","x":0,"y":0},
			{"res":"f0005","x":0,"y":0},
			{"res":"f0006","x":0,"y":0},
			{"res":"f0007","x":0,"y":0},
			{"res":"f0008","x":0,"y":0},
			{"res":"f0009","x":0,"y":0}
		]
	}
}
}